faster_etapr/__init__.py
faster_etapr/etapr.py
faster_etapr/types.py
faster_etapr/utils.py
faster_etapr-0.1.2.dist-info/METADATA
faster_etapr-0.1.2.dist-info/WHEEL
faster_etapr-0.1.2.dist-info/licenses/LICENSE
faster_etapr-0.1.2.dist-info/RECORD
