Metadata-Version: 2.3
Name: faster-eTaPR
Version: 0.1.2
Dynamic: Summary
Project-URL: Documentation, https://faster-etapr.readthedocs.io
Project-URL: Source, https://github.com/GPla/faster-eTaPR
Author-email: Gorden Platz <36087062+GPla@users.noreply.github.com>
License-Expression: MIT
License-File: LICENSE
Keywords: anomaly,detection,etapr,evaluation,learning,machine,metrics,performance,point-adjust
Classifier: Intended Audience :: Science/Research
Classifier: License :: OSI Approved :: MIT License
Classifier: Operating System :: OS Independent
Classifier: Programming Language :: Python :: 3.10
Classifier: Programming Language :: Python :: 3.11
Classifier: Programming Language :: Python :: 3.12
Classifier: Topic :: Scientific/Engineering :: Artificial Intelligence
Classifier: Topic :: Software Development :: Libraries
Requires-Python: >=3.10
Requires-Dist: einops>=0.7.0
Requires-Dist: mlnext-framework>=0.4.1
Requires-Dist: numpy>=1.26.4
Provides-Extra: docs
Requires-Dist: furo>=2024.01.29; extra == 'docs'
Requires-Dist: myst-parser>=2.0.0; extra == 'docs'
Requires-Dist: rinohtype>=0.5.4; extra == 'docs'
Requires-Dist: sphinx-copybutton>=0.5.2; extra == 'docs'
Requires-Dist: sphinx>=7.2.6; extra == 'docs'
Provides-Extra: tests
Requires-Dist: pytest-cov>=5.0.0; extra == 'tests'
Requires-Dist: pytest-mock>=3.14.0; extra == 'tests'
Requires-Dist: pytest>=8.1.1; extra == 'tests'
